inceses/__init__.py
inceses/main.py
inceses-1.0.dist-info/licenses/LICENSE
inceses-1.0.dist-info/METADATA
inceses-1.0.dist-info/WHEEL
inceses-1.0.dist-info/top_level.txt
inceses-1.0.dist-info/RECORD
